{
    "data": [{
            "id": 1,
            "country": "Togo",
            "developer": "Kerluke, Howe and Hammes PLC",
            "project_name": "Wuckert, Blanda and Crooks",
            "sector": "Institutional/Public Sector",
            "address": "16 Mohr Street 36215 AdamVille",
            "region": "SvenVille",
            "lga": "KamronVille",
            "status": "On hold",
            "main_contractor": "Gleason Group and Sons",
            "architect": "Macejkovic-Donnelly Inc",
            "quantity_surveyor": "Weimann, Douglas and Mertz PLC",
            "structural_engineers": "Turcotte, Sawayn and Hansen Group",
            "mep_engineer": "Howell-Hermiston LLC",
            "project_manager": "Reichert, Oberbrunner and Hettinger and Sons",
            "lift_contractor": "Zemlak, Hane and Kutch and Sons",
            "bulk_earth_contractor": "Kuvalis Inc Group",
            "other": null,
            "author": 1,
            "content_status": "publish",
            "deleted_at": null,
            "created_at": "2019-12-10 17:28:33",
            "updated_at": "2019-12-10 17:28:33",
            "latitude": "-75.287715",
            "longitude": "63.447841",
            "est_range": "$3M - $46M",
            "state": "Wyoming",
            "floors": 3,
            "elec_engineer": "Towne PLC Ltd",
            "piling_contractor": "O'Connell Ltd and Sons",
            "legal_partners": "Kutch-Watsica PLC"
        },
        {
            "id": 2,
            "country": "Nigeria",
            "developer": "Jacobs, Wiegand and Lind LLC",
            "project_name": "Baumbach, Toy and Littel",
            "sector": "Institutional/Public Sector",
            "address": "71 Dicki Street 00948 BettyeVille",
            "region": "ArchibaldVille",
            "lga": "GermanVille",
            "status": "On hold",
            "main_contractor": "Murray-Sanford LLC",
            "architect": "Graham Group Group",
            "quantity_surveyor": "Nitzsche Inc Group",
            "structural_engineers": "Ruecker Ltd LLC",
            "mep_engineer": "Muller, Block and Rau Group",
            "project_manager": "Morar-Bode Inc",
            "lift_contractor": "Quitzon LLC Inc",
            "bulk_earth_contractor": "Ratke-Thiel LLC",
            "other": null,
            "author": 1,
            "content_status": "publish",
            "deleted_at": null,
            "created_at": "2019-12-10 17:28:33",
            "updated_at": "2019-12-10 17:28:33",
            "latitude": "47.865983",
            "longitude": "-89.370544",
            "est_range": "$10M - $35M",
            "state": "Hawaii",
            "floors": 7,
            "elec_engineer": "Abernathy-Labadie Inc",
            "piling_contractor": "Medhurst, Bauch and Homenick Inc",
            "legal_partners": "White-Spencer Ltd"
        },
        {
            "id": 3,
            "country": "Togo",
            "developer": "Turner-Orn LLC",
            "project_name": "Beatty-Mraz",
            "sector": "Retail",
            "address": "96 Strosin Street 84731 GeneVille",
            "region": "ReynaVille",
            "lga": "CitlalliVille",
            "status": "Site Clearing",
            "main_contractor": "Lynch-Armstrong Inc",
            "architect": "Fisher, Leffler and Jenkins and Sons",
            "quantity_surveyor": "Ratke, Ward and O'Reilly Inc",
            "structural_engineers": "Gutmann Ltd LLC",
            "mep_engineer": "Crist, Klein and Rutherford Ltd",
            "project_manager": "O'Reilly-Jacobi and Sons",
            "lift_contractor": "Berge PLC LLC",
            "bulk_earth_contractor": "Hilpert, Turcotte and Jacobson PLC",
            "other": null,
            "author": 1,
            "content_status": "publish",
            "deleted_at": null,
            "created_at": "2019-12-10 17:28:33",
            "updated_at": "2019-12-10 17:28:33",
            "latitude": "23.414543",
            "longitude": "-143.497474",
            "est_range": "$7M - $22M",
            "state": "Iowa",
            "floors": 5,
            "elec_engineer": "Pollich-Waters Ltd",
            "piling_contractor": "Roob Group PLC",
            "legal_partners": "Zieme, Douglas and Bailey Inc"
        },
        {
            "id": 4,
            "country": "Nigeria",
            "developer": "Miller-Considine LLC",
            "project_name": "Morissette PLC",
            "sector": "Office",
            "address": "29 Brekke Street 48483 CollinVille",
            "region": "ReynaVille",
            "lga": "HarleyVille",
            "status": "Completed",
            "main_contractor": "Kozey, Hansen and Price LLC",
            "architect": "Goodwin PLC Inc",
            "quantity_surveyor": "Steuber-Reichel and Sons",
            "structural_engineers": "Schoen-Rice Inc",
            "mep_engineer": "White Inc LLC",
            "project_manager": "Bernhard Inc LLC",
            "lift_contractor": "Balistreri-Douglas PLC",
            "bulk_earth_contractor": "Kessler and Sons PLC",
            "other": null,
            "author": 1,
            "content_status": "publish",
            "deleted_at": null,
            "created_at": "2019-12-10 17:28:33",
            "updated_at": "2019-12-10 17:28:33",
            "latitude": "88.008399",
            "longitude": "103.65787",
            "est_range": "$3M - $47M",
            "state": "North Dakota",
            "floors": 1,
            "elec_engineer": "Greenfelder, Howe and Rippin Ltd",
            "piling_contractor": "Oberbrunner and Sons Group",
            "legal_partners": "Nikolaus, Gibson and Bradtke PLC"
        },
        {
            "id": 5,
            "country": "Ivory Coast",
            "developer": "Harvey, Weimann and Ullrich PLC",
            "project_name": "Wisozk Group",
            "sector": "Industrial",
            "address": "48 Wiegand Street 27045 DinoVille",
            "region": "BrielleVille",
            "lga": "CitlalliVille",
            "status": "Site Clearing",
            "main_contractor": "Emard-Bosco PLC",
            "architect": "Toy-Considine Group",
            "quantity_surveyor": "Tillman, Cassin and Goodwin PLC",
            "structural_engineers": "Mills, Botsford and Miller Ltd",
            "mep_engineer": "Bayer-Strosin LLC",
            "project_manager": "Schumm LLC Ltd",
            "lift_contractor": "Reichel-Weber and Sons",
            "bulk_earth_contractor": "Pollich LLC LLC",
            "other": null,
            "author": 1,
            "content_status": "publish",
            "deleted_at": null,
            "created_at": "2019-12-10 17:28:33",
            "updated_at": "2019-12-10 17:28:33",
            "latitude": "-27.987693",
            "longitude": "-162.65884",
            "est_range": "$10M - $24M",
            "state": "Virginia",
            "floors": 7,
            "elec_engineer": "Kuhn, Hodkiewicz and Murray LLC",
            "piling_contractor": "Johnston and Sons Ltd",
            "legal_partners": "Hessel, Collier and Purdy and Sons"
        },
        {
            "id": 6,
            "country": "Ghana",
            "developer": "Wunsch-Stiedemann LLC",
            "project_name": "Bergnaum, Harvey and Greenfelder",
            "sector": "Retail",
            "address": "79 Borer Street 19313 ElinorVille",
            "region": "GermanVille",
            "lga": "CitlalliVille",
            "status": "Completed",
            "main_contractor": "Ward, Kiehn and West PLC",
            "architect": "Hintz-Mosciski and Sons",
            "quantity_surveyor": "Gleason, Daugherty and Jenkins and Sons",
            "structural_engineers": "Mraz and Sons Inc",
            "mep_engineer": "Volkman PLC PLC",
            "project_manager": "Yundt Inc Ltd",
            "lift_contractor": "Aufderhar-Goodwin Ltd",
            "bulk_earth_contractor": "Smitham-Friesen Inc",
            "other": null,
            "author": 1,
            "content_status": "publish",
            "deleted_at": null,
            "created_at": "2019-12-10 17:28:33",
            "updated_at": "2019-12-10 17:28:33",
            "latitude": "53.514852",
            "longitude": "169.374538",
            "est_range": "$5M - $38M",
            "state": "Alabama",
            "floors": 3,
            "elec_engineer": "Wintheiser, Satterfield and Schroeder PLC",
            "piling_contractor": "Schamberger LLC Inc",
            "legal_partners": "Lakin Group Inc"
        },
        {
            "id": 7,
            "country": "Ivory Coast",
            "developer": "Rowe, Pollich and Predovic LLC",
            "project_name": "Gottlieb, Runolfsson and Baumbach",
            "sector": "Institutional/Public Sector",
            "address": "79 Christiansen Street 17875 TomasaVille",
            "region": "BrielleVille",
            "lga": "SantiagoVille",
            "status": "Site Clearing",
            "main_contractor": "Jakubowski Group and Sons",
            "architect": "Lebsack PLC Group",
            "quantity_surveyor": "Miller-Legros LLC",
            "structural_engineers": "Zemlak and Sons and Sons",
            "mep_engineer": "Wintheiser Ltd Inc",
            "project_manager": "Kshlerin Inc LLC",
            "lift_contractor": "Prohaska, Emard and Wolff Group",
            "bulk_earth_contractor": "O'Connell-Kessler LLC",
            "other": null,
            "author": 1,
            "content_status": "publish",
            "deleted_at": null,
            "created_at": "2019-12-10 17:28:33",
            "updated_at": "2019-12-10 17:28:33",
            "latitude": "25.655873",
            "longitude": "-109.495188",
            "est_range": "$9M - $34M",
            "state": "North Dakota",
            "floors": 3,
            "elec_engineer": "Zulauf-Jacobson PLC",
            "piling_contractor": "Wilkinson Group Group",
            "legal_partners": "West Group Group"
        },
        {
            "id": 8,
            "country": "Nigeria",
            "developer": "McCullough, Beatty and Wilkinson and Sons",
            "project_name": "Shields-Mayert",
            "sector": "Industrial",
            "address": "43 McCullough Street 47820 DeionVille",
            "region": "ArchibaldVille",
            "lga": "EstherVille",
            "status": "Under construction",
            "main_contractor": "West-Fahey and Sons",
            "architect": "Powlowski and Sons LLC",
            "quantity_surveyor": "Lynch LLC PLC",
            "structural_engineers": "Gusikowski PLC Inc",
            "mep_engineer": "Cummerata Group and Sons",
            "project_manager": "Schuster-Klocko Group",
            "lift_contractor": "Lueilwitz-Greenholt LLC",
            "bulk_earth_contractor": "Flatley Inc PLC",
            "other": null,
            "author": 1,
            "content_status": "publish",
            "deleted_at": null,
            "created_at": "2019-12-10 17:28:33",
            "updated_at": "2019-12-10 17:28:33",
            "latitude": "-56.106225",
            "longitude": "50.997314",
            "est_range": "$8M - $18M",
            "state": "Indiana",
            "floors": 6,
            "elec_engineer": "Ruecker PLC Group",
            "piling_contractor": "Beier Inc PLC",
            "legal_partners": "Zieme LLC Inc"
        },
        {
            "id": 9,
            "country": "Ghana",
            "developer": "Fahey-Torphy LLC",
            "project_name": "Kiehn-Will",
            "sector": "Institutional/Public Sector",
            "address": "93 Kuhic Street 83061 HalleVille",
            "region": "BrielleVille",
            "lga": "KennithVille",
            "status": "On hold",
            "main_contractor": "Connelly-Larkin Ltd",
            "architect": "Gulgowski-Langworth LLC",
            "quantity_surveyor": "Wisoky-Hammes PLC",
            "structural_engineers": "Feil-Fadel LLC",
            "mep_engineer": "Douglas, Schowalter and Collins Ltd",
            "project_manager": "Rogahn Ltd Ltd",
            "lift_contractor": "Gerhold-Quitzon PLC",
            "bulk_earth_contractor": "Skiles Ltd Ltd",
            "other": null,
            "author": 1,
            "content_status": "publish",
            "deleted_at": null,
            "created_at": "2019-12-10 17:28:33",
            "updated_at": "2019-12-10 17:28:33",
            "latitude": "41.751174",
            "longitude": "-115.102084",
            "est_range": "$4M - $36M",
            "state": "Alabama",
            "floors": 3,
            "elec_engineer": "Mayert, Watsica and O'Keefe PLC",
            "piling_contractor": "Hill LLC Group",
            "legal_partners": "D'Amore PLC Ltd"
        },
        {
            "id": 10,
            "country": "Ivory Coast",
            "developer": "Toy-Stroman Ltd",
            "project_name": "Miller-Beier",
            "sector": "Institutional/Public Sector",
            "address": "26 Klein Street 99453 KurtisVille",
            "region": "SvenVille",
            "lga": "EleazarVille",
            "status": "Site Clearing",
            "main_contractor": "Goldner-Tremblay Group",
            "architect": "Hauck, Runolfsson and Ullrich Inc",
            "quantity_surveyor": "Kertzmann Ltd Inc",
            "structural_engineers": "Hane, Heathcote and Emard Group",
            "mep_engineer": "Halvorson PLC Inc",
            "project_manager": "Kuhn-Schinner PLC",
            "lift_contractor": "Reinger, Harvey and Senger PLC",
            "bulk_earth_contractor": "Tromp Group Inc",
            "other": null,
            "author": 1,
            "content_status": "publish",
            "deleted_at": null,
            "created_at": "2019-12-10 17:28:33",
            "updated_at": "2019-12-10 17:28:33",
            "latitude": "7.222692",
            "longitude": "63.342728",
            "est_range": "$7M - $48M",
            "state": "Alabama",
            "floors": 9,
            "elec_engineer": "Sanford-Parker Ltd",
            "piling_contractor": "Schuppe PLC Group",
            "legal_partners": "Satterfield-Conn Inc"
        },
        {
            "id": 11,
            "country": "Ivory Coast",
            "developer": "Rodriguez Ltd Group",
            "project_name": "Bahringer-Sporer",
            "sector": "Retail",
            "address": "22 Halvorson Street 75173 TatumVille",
            "region": "SvenVille",
            "lga": "EstherVille",
            "status": "On hold",
            "main_contractor": "Kirlin-Schinner LLC",
            "architect": "Erdman-Auer LLC",
            "quantity_surveyor": "Cartwright Inc and Sons",
            "structural_engineers": "Larkin Ltd Ltd",
            "mep_engineer": "Crist, Cremin and Hahn PLC",
            "project_manager": "Lesch, Von and Abernathy and Sons",
            "lift_contractor": "Kuhic, Becker and Schowalter PLC",
            "bulk_earth_contractor": "Schiller LLC Inc",
            "other": null,
            "author": 1,
            "content_status": "publish",
            "deleted_at": null,
            "created_at": "2019-12-10 17:28:33",
            "updated_at": "2019-12-10 17:28:33",
            "latitude": "17.971181",
            "longitude": "148.854159",
            "est_range": "$9M - $18M",
            "state": "North Dakota",
            "floors": 4,
            "elec_engineer": "Hermiston-Pagac and Sons",
            "piling_contractor": "Schimmel, Thiel and Kerluke Ltd",
            "legal_partners": "Gottlieb, Hettinger and Cartwright Inc"
        },
        {
            "id": 12,
            "country": "Ghana",
            "developer": "Lakin Inc LLC",
            "project_name": "Simonis, Runolfsdottir and Kertzmann",
            "sector": "Retail",
            "address": "24 Marquardt Street 99680 BernadetteVille",
            "region": "DorisVille",
            "lga": "CitlalliVille",
            "status": "Site Clearing",
            "main_contractor": "Prosacco, O'Conner and Shanahan Group",
            "architect": "Zboncak-Sanford Group",
            "quantity_surveyor": "Fisher-Rolfson LLC",
            "structural_engineers": "Reichel, Eichmann and Kuvalis Ltd",
            "mep_engineer": "Sanford LLC PLC",
            "project_manager": "Deckow, Gislason and Wilderman Inc",
            "lift_contractor": "Ernser-Reinger PLC",
            "bulk_earth_contractor": "Lehner and Sons Group",
            "other": null,
            "author": 1,
            "content_status": "publish",
            "deleted_at": null,
            "created_at": "2019-12-10 17:28:33",
            "updated_at": "2019-12-10 17:28:33",
            "latitude": "-35.04784",
            "longitude": "106.346828",
            "est_range": "$9M - $42M",
            "state": "Indiana",
            "floors": 5,
            "elec_engineer": "Kuhlman Inc and Sons",
            "piling_contractor": "Carroll, Collier and Strosin and Sons",
            "legal_partners": "Stoltenberg-Rempel PLC"
        },
        {
            "id": 13,
            "country": "Kenya",
            "developer": "Bergnaum, Gutkowski and Ziemann PLC",
            "project_name": "Strosin, Keeling and Altenwerth",
            "sector": "Industrial",
            "address": "53 Ryan Street 90580 ElodyVille",
            "region": "SvenVille",
            "lga": "EstherVille",
            "status": "Under construction",
            "main_contractor": "Tremblay, Brekke and Blick and Sons",
            "architect": "Runolfsdottir-Thompson LLC",
            "quantity_surveyor": "Haley PLC Inc",
            "structural_engineers": "Bode-Lynch Group",
            "mep_engineer": "Wilkinson PLC Group",
            "project_manager": "Schiller-Bashirian and Sons",
            "lift_contractor": "Wunsch Inc Group",
            "bulk_earth_contractor": "Baumbach, Sanford and Schimmel Group",
            "other": null,
            "author": 1,
            "content_status": "publish",
            "deleted_at": null,
            "created_at": "2019-12-10 17:28:33",
            "updated_at": "2019-12-10 17:28:33",
            "latitude": "39.87553",
            "longitude": "157.247775",
            "est_range": "$5M - $19M",
            "state": "Wyoming",
            "floors": 6,
            "elec_engineer": "Abernathy Group Inc",
            "piling_contractor": "Buckridge-Dibbert Ltd",
            "legal_partners": "Armstrong LLC PLC"
        },
        {
            "id": 14,
            "country": "Kenya",
            "developer": "Schumm, Rutherford and Wuckert and Sons",
            "project_name": "Cruickshank LLC",
            "sector": "Industrial",
            "address": "46 Stark Street 20237 SibylVille",
            "region": "GarthVille",
            "lga": "KamronVille",
            "status": "Conceptual",
            "main_contractor": "Windler, Legros and Spencer Ltd",
            "architect": "Beahan-Labadie Ltd",
            "quantity_surveyor": "Lemke LLC Group",
            "structural_engineers": "Volkman-Bashirian and Sons",
            "mep_engineer": "Kshlerin Ltd PLC",
            "project_manager": "Robel LLC and Sons",
            "lift_contractor": "Bauch LLC PLC",
            "bulk_earth_contractor": "Durgan and Sons and Sons",
            "other": null,
            "author": 1,
            "content_status": "publish",
            "deleted_at": null,
            "created_at": "2019-12-10 17:28:33",
            "updated_at": "2019-12-10 17:28:33",
            "latitude": "-47.636458",
            "longitude": "-123.429187",
            "est_range": "$6M - $40M",
            "state": "Indiana",
            "floors": 0,
            "elec_engineer": "Bauch, Daniel and Hickle LLC",
            "piling_contractor": "Greenholt-Zulauf and Sons",
            "legal_partners": "Keebler, Ebert and Conn PLC"
        },
        {
            "id": 15,
            "country": "Nigeria",
            "developer": "Kiehn, Crona and Little Group",
            "project_name": "Funk-Grimes",
            "sector": "Retail",
            "address": "84 O'Hara Street 15713 OmaVille",
            "region": "ArchibaldVille",
            "lga": "CitlalliVille",
            "status": "Conceptual",
            "main_contractor": "Deckow-Reynolds and Sons",
            "architect": "Padberg, VonRueden and Lubowitz LLC",
            "quantity_surveyor": "Huels-Haley LLC",
            "structural_engineers": "Hessel-Blanda Ltd",
            "mep_engineer": "Leuschke, Pacocha and Mayer Inc",
            "project_manager": "Bode-Thompson Group",
            "lift_contractor": "Reinger Group Inc",
            "bulk_earth_contractor": "Hintz, Little and Barrows and Sons",
            "other": null,
            "author": 1,
            "content_status": "publish",
            "deleted_at": null,
            "created_at": "2019-12-10 17:28:33",
            "updated_at": "2019-12-10 17:28:33",
            "latitude": "-23.686254",
            "longitude": "-76.978161",
            "est_range": "$6M - $21M",
            "state": "Iowa",
            "floors": 2,
            "elec_engineer": "Nolan-Leffler Inc",
            "piling_contractor": "Vandervort, Brekke and Morar Inc",
            "legal_partners": "Runolfsdottir, Bashirian and Hilpert and Sons"
        }
    ],
    "links": {
        "self": "link-value",
        "first": "https://70c5b72c-65db-4a66-ba01-3e14763157e8.mock.pstmn.io?page=1",
        "last": "https://70c5b72c-65db-4a66-ba01-3e14763157e8.mock.pstmn.io?page=3",
        "prev": null,
        "next": "https://70c5b72c-65db-4a66-ba01-3e14763157e8.mock.pstmn.io?page=2"
    },
    "meta": {
        "current_page": 1,
        "from": 1,
        "last_page": 3,
        "path": "https://70c5b72c-65db-4a66-ba01-3e14763157e8.mock.pstmn.io",
        "per_page": 15,
        "to": 15,
        "total": 45
    },
    "filters": {
        "lga": [
            "KamronVille",
            "GermanVille",
            "CitlalliVille",
            "HarleyVille",
            "SantiagoVille",
            "EstherVille",
            "KennithVille",
            "EleazarVille",
            "KarleeVille",
            "AriVille"
        ],
        "region": [
            "SvenVille",
            "ArchibaldVille",
            "ReynaVille",
            "BrielleVille",
            "GermanVille",
            "DorisVille",
            "GarthVille",
            "LaronVille",
            "ReinaVille",
            "MafaldaVille"
        ],
        "status": [
            "On hold",
            "Site Clearing",
            "Completed",
            "Under construction",
            "Conceptual",
            "Implementation"
        ],
        "sector": [
            "Institutional/Public Sector",
            "Retail",
            "Office",
            "Industrial",
            "Hospitality"
        ],
        "state": [
            "Wyoming",
            "Hawaii",
            "Iowa",
            "North Dakota",
            "Virginia",
            "Alabama",
            "Indiana",
            "Oklahoma",
            "New Mexico"
        ],
        "est_range": [
            "$3M - $46M",
            "$10M - $35M",
            "$7M - $22M",
            "$3M - $47M",
            "$10M - $24M",
            "$5M - $38M",
            "$9M - $34M",
            "$8M - $18M",
            "$4M - $36M",
            "$7M - $48M",
            "$9M - $18M",
            "$9M - $42M",
            "$5M - $19M",
            "$6M - $40M",
            "$6M - $21M",
            "$8M - $20M",
            "$6M - $25M",
            "$2M - $31M",
            "$6M - $41M",
            "$6M - $39M",
            "$7M - $17M",
            "$7M - $30M",
            "$10M - $37M",
            "$10M - $28M",
            "$2M - $17M",
            "$5M - $28M",
            "$5M - $17M",
            "$6M - $26M",
            "$8M - $32M",
            "$1M - $48M",
            "$9M - $36M",
            "$2M - $49M",
            "$3M - $26M",
            "$5M - $21M",
            "$0M - $33M",
            "$8M - $27M",
            "$6M - $48M",
            "$5M - $46M",
            "$5M - $48M",
            "$0M - $39M",
            "$8M - $48M",
            "$3M - $22M",
            "$10M - $49M",
            "$1M - $36M",
            "$7M - $20M",
            "$7M - $32M",
            "$6M - $20M",
            "$4M - $33M",
            "$2M - $40M",
            "$3M - $32M",
            "$4M - $21M",
            "$1M - $47M",
            "$9M - $23M",
            "$10M - $27M",
            "$9M - $50M",
            "$7M - $42M",
            "$8M - $43M",
            "$10M - $41M",
            "$7M - $36M",
            "$8M - $16M",
            "$5M - $26M",
            "$1M - $44M",
            "$10M - $26M",
            "$0M - $49M",
            "$6M - $24M",
            "$8M - $25M",
            "$8M - $49M",
            "$3M - $25M",
            "$2M - $28M",
            "$7M - $46M",
            "$9M - $31M",
            "$6M - $44M",
            "$7M - $26M",
            "$7M - $31M",
            "$9M - $40M",
            "$0M - $43M",
            "$8M - $31M",
            "$8M - $15M",
            "$10M - $34M",
            "$0M - $37M",
            "$5M - $47M",
            "$6M - $23M",
            "$8M - $34M",
            "$8M - $19M",
            "$1M - $45M",
            "$7M - $18M",
            "$0M - $23M",
            "$7M - $37M",
            "$9M - $20M",
            "$8M - $47M",
            "$10M - $33M",
            "$6M - $31M",
            "$2M - $46M",
            "$5M - $50M",
            "$0M - $50M",
            "$8M - $44M",
            "$5M - $35M",
            "$6M - $17M",
            "$10M - $31M",
            "$0M - $32M",
            "$4M - $35M",
            "$3M - $16M",
            "$9M - $33M",
            "$8M - $29M",
            "$10M - $45M",
            "$10M - $20M",
            "$5M - $24M",
            "$4M - $16M",
            "$6M - $18M",
            "$6M - $36M",
            "$9M - $47M",
            "$0M - $27M",
            "$1M - $42M",
            "$8M - $50M",
            "$4M - $39M",
            "$6M - $49M",
            "$3M - $43M",
            "$4M - $49M",
            "$0M - $45M",
            "$1M - $37M",
            "$1M - $46M",
            "$6M - $29M",
            "$0M - $28M",
            "$10M - $46M",
            "$10M - $40M",
            "$0M - $17M",
            "$4M - $34M",
            "$1M - $49M",
            "$1M - $30M",
            "$0M - $42M",
            "$7M - $23M",
            "$1M - $34M",
            "$10M - $23M",
            "$10M - $19M",
            "$6M - $34M",
            "$1M - $18M",
            "$4M - $15M",
            "$8M - $40M",
            "$9M - $48M",
            "$4M - $27M",
            "$2M - $27M",
            "$7M - $33M",
            "$5M - $42M",
            "$6M - $15M",
            "$2M - $38M",
            "$6M - $47M",
            "$0M - $29M",
            "$0M - $16M",
            "$8M - $23M",
            "$9M - $43M",
            "$5M - $37M",
            "$6M - $33M",
            "$10M - $29M",
            "$10M - $25M",
            "$1M - $24M",
            "$4M - $48M",
            "$3M - $34M",
            "$1M - $27M",
            "$7M - $40M",
            "$3M - $45M",
            "$4M - $41M",
            "$0M - $44M",
            "$2M - $39M",
            "$10M - $50M",
            "$10M - $18M",
            "$1M - $25M",
            "$3M - $38M",
            "$7M - $29M",
            "$8M - $42M",
            "$2M - $45M",
            "$7M - $47M",
            "$3M - $35M",
            "$6M - $43M",
            "$7M - $45M",
            "$10M - $22M",
            "$4M - $32M",
            "$10M - $32M",
            "$0M - $25M",
            "$9M - $39M",
            "$8M - $45M",
            "$8M - $26M",
            "$3M - $37M",
            "$3M - $36M",
            "$5M - $25M",
            "$0M - $26M",
            "$0M - $24M",
            "$5M - $15M",
            "$4M - $28M",
            "$9M - $25M",
            "$1M - $32M",
            "$0M - $21M",
            "$9M - $28M",
            "$9M - $24M",
            "$4M - $38M",
            "$1M - $23M",
            "$0M - $47M",
            "$0M - $30M",
            "$6M - $38M",
            "$9M - $17M",
            "$1M - $21M",
            "$9M - $41M",
            "$7M - $43M",
            "$1M - $16M",
            "$1M - $43M",
            "$7M - $24M",
            "$5M - $33M",
            "$6M - $45M",
            "$3M - $44M",
            "$0M - $36M",
            "$4M - $50M",
            "$4M - $37M",
            "$2M - $50M",
            "$3M - $17M",
            "$2M - $44M",
            "$5M - $45M",
            "$8M - $46M",
            "$7M - $49M",
            "$10M - $39M",
            "$7M - $35M",
            "$0M - $34M",
            "$6M - $37M",
            "$2M - $19M",
            "$7M - $34M",
            "$6M - $16M",
            "$1M - $17M",
            "$9M - $26M",
            "$3M - $28M",
            "$8M - $37M",
            "$1M - $40M",
            "$8M - $38M",
            "$4M - $40M",
            "$3M - $48M",
            "$9M - $32M",
            "$8M - $17M",
            "$7M - $44M",
            "$3M - $15M",
            "$4M - $25M",
            "$3M - $18M",
            "$0M - $41M",
            "$6M - $19M",
            "$9M - $27M",
            "$1M - $26M",
            "$3M - $40M",
            "$0M - $48M",
            "$2M - $16M",
            "$9M - $16M",
            "$4M - $17M",
            "$2M - $35M",
            "$2M - $43M",
            "$0M - $31M",
            "$4M - $19M",
            "$5M - $32M",
            "$4M - $42M",
            "$6M - $50M",
            "$6M - $42M",
            "$8M - $39M",
            "$6M - $32M",
            "$9M - $38M",
            "$8M - $22M",
            "$3M - $50M",
            "$9M - $15M",
            "$8M - $33M",
            "$0M - $15M",
            "$3M - $49M",
            "$10M - $44M",
            "$2M - $41M",
            "$3M - $20M",
            "$5M - $43M",
            "$10M - $21M",
            "$8M - $30M",
            "$3M - $31M",
            "$5M - $16M",
            "$1M - $28M",
            "$2M - $18M",
            "$2M - $47M",
            "$3M - $33M",
            "$7M - $16M",
            "$9M - $19M",
            "$3M - $21M",
            "$10M - $48M",
            "$4M - $31M",
            "$4M - $47M",
            "$5M - $36M",
            "$2M - $15M",
            "$7M - $38M",
            "$0M - $35M",
            "$4M - $24M",
            "$8M - $35M"
        ],
        "country_name": [
            "Togo",
            "Nigeria",
            "Ivory Coast",
            "Ghana",
            "Kenya"
        ]
    }
}